MANIFEST.in
README.rst
setup.py
bpylist/__init__.py
bpylist/archive_types.py
bpylist/archiver.py
bpylist.egg-info/PKG-INFO
bpylist.egg-info/SOURCES.txt
bpylist.egg-info/dependency_links.txt
bpylist.egg-info/top_level.txt
src/bplist.c