Metadata-Version: 1.1
Name: bpylist
Version: 0.1.4
Summary: parse and generate binary plists and NSKeyedArchiver archives
Home-page: https://github.com/marketcircle/bpylist
Author: Marketcircle Inc.
Author-email: cloud@marketcircle.com
License: UNKNOWN
Platform: UNKNOWN
Classifier: Development Status :: 5 - Production/Stable
Classifier: Programming Language :: Python :: 3.6
Classifier: Intended Audience :: Developers
Classifier: Topic :: Software Development :: Libraries
